{
  "resources": {
    "express": {
      "packages": {
        "body-parser": true,
        "merge-descriptors": true,
        "serve-static": true,
        "finalhandler": true,
        "methods": true,
        "debug": true,
        "depd": true,
        "array-flatten": true,
        "utils-merge": true,
        "setprototypeof": true,
        "parseurl": true,
        "accepts": true,
        "type-is": true,
        "fresh": true,
        "range-parser": true,
        "proxy-addr": true,
        "qs": true,
        "safe-buffer": true,
        "content-disposition": true,
        "encodeurl": true,
        "escape-html": true,
        "on-finished": true,
        "statuses": true,
        "cookie-signature": true,
        "cookie": true,
        "send": true,
        "vary": true,
        "content-type": true,
        "etag": true,
        "path-to-regexp": true
      },
      "globals": {
        "process.env.NODE_ENV": true,
        "console.error": true,
        "setImmediate": true
      },
      "builtin": {
        "events.EventEmitter.prototype": true,
        "fs.statSync": true,
        "http.IncomingMessage.prototype": true,
        "http.ServerResponse.prototype": true,
        "http.createServer": true,
        "net.isIP": true,
        "path.basename": true,
        "path.dirname": true,
        "path.extname": true,
        "path.join": true,
        "path.resolve": true,
        "querystring.parse": true
      }
    },
    "body-parser": {
      "packages": {
        "depd": true,
        "bytes": true,
        "content-type": true,
        "http-errors": true,
        "debug": true,
        "type-is": true,
        "qs": true,
        "raw-body": true,
        "iconv-lite": true,
        "on-finished": true
      },
      "builtin": {
        "querystring": true,
        "zlib.createGunzip": true,
        "zlib.createInflate": true
      }
    },
    "cors": {
      "packages": {
        "object-assign": true,
        "vary": true
      }
    },
    "express-rate-limit": {
      "globals": {
        "setInterval": true
      }
    },
    "ethjs-query": {
      "packages": {
        "ethjs-format": true,
        "ethjs-rpc": true,
        "promise-to-callback": true
      },
      "globals": {
        "console": true
      }
    },
    "ethereumjs-util": {
      "packages": {
        "ethjs-util": true,
        "bn.js": true,
        "ethereum-cryptography": true,
        "create-hash": true,
        "rlp": true,
        "safe-buffer": true,
        "elliptic": true
      },
      "globals": {
        "Buffer": true
      },
      "builtin": {
        "assert": true,
        "buffer.Buffer.from": true
      }
    },
    "@pablopunk/geo-ip": {
      "packages": {
        "maxmind-db-reader": true,
        "auto-bind": true
      },
      "globals": {
        "__dirname": true
      }
    },
    "emoji-flag": {
      "packages": {
        "punycode2": true
      }
    },
    "events": {
      "globals": {
        "console": true
      }
    },
    "ethjs-format": {
      "packages": {
        "ethjs-schema": true,
        "ethjs-util": true,
        "number-to-bn": true,
        "strip-hex-prefix": true
      }
    },
    "ethjs-rpc": {
      "packages": {
        "promise-to-callback": true
      }
    },
    "promise-to-callback": {
      "packages": {
        "is-fn": true,
        "set-immediate-shim": true
      }
    },
    "bn.js": {
      "builtin": {
        "buffer.Buffer": true
      }
    },
    "ethjs-util": {
      "packages": {
        "is-hex-prefixed": true,
        "strip-hex-prefix": true
      },
      "globals": {
        "Buffer": true
      }
    },
    "maxmind-db-reader": {
      "packages": {
        "big-integer": true,
        "ip-address": true
      },
      "globals": {
        "Buffer": true,
        "process.nextTick": true
      },
      "builtin": {
        "fs.readFile": true,
        "fs.readFileSync": true
      }
    },
    "web3-provider-engine": {
      "packages": {
        "ethereumjs-util": true,
        "eth-block-tracker": true,
        "async": true,
        "xhr": true,
        "request": true,
        "eth-json-rpc-errors": true,
        "ethereumjs-tx": true,
        "eth-sig-util": true,
        "xtend": true,
        "json-stable-stringify": true,
        "semaphore": true
      },
      "globals": {
        "console.log": true,
        "setTimeout": true,
        "process.browser": true,
        "console.error": true,
        "Buffer.from": true,
        "console.warn": true
      },
      "builtin": {
        "events.EventEmitter": true,
        "util.inherits": true
      }
    },
    "serve-static": {
      "packages": {
        "encodeurl": true,
        "escape-html": true,
        "parseurl": true,
        "send": true
      },
      "globals": {
        "Buffer.byteLength": true
      },
      "builtin": {
        "path.resolve": true,
        "url.format": true
      }
    },
    "http-errors": {
      "packages": {
        "depd": true,
        "setprototypeof": true,
        "statuses": true,
        "inherits": true,
        "toidentifier": true
      }
    },
    "debug": {
      "packages": {
        "ms": true
      },
      "globals": {
        "process": true,
        "chrome": true,
        "console": true,
        "localStorage": true,
        "document": true,
        "navigator": true
      },
      "builtin": {
        "fs.SyncWriteStream": true,
        "net.Socket": true,
        "tty.WriteStream": true,
        "tty.isatty": true,
        "util": true
      }
    },
    "type-is": {
      "packages": {
        "media-typer": true,
        "mime-types": true
      }
    },
    "number-to-bn": {
      "packages": {
        "bn.js": true,
        "strip-hex-prefix": true
      }
    },
    "strip-hex-prefix": {
      "packages": {
        "is-hex-prefixed": true
      }
    },
    "set-immediate-shim": {
      "globals": {
        "setImmediate": true,
        "setTimeout.apply": true
      }
    },
    "ethereum-cryptography": {
      "packages": {
        "secp256k1": true,
        "keccak": true,
        "randombytes": true
      },
      "globals": {
        "Buffer.from": true
      }
    },
    "create-hash": {
      "builtin": {
        "crypto.createHash": true
      }
    },
    "rlp": {
      "packages": {
        "bn.js": true
      },
      "globals": {
        "Buffer.concat": true,
        "Buffer.from": true,
        "Buffer.isBuffer": true
      }
    },
    "eth-block-tracker": {
      "packages": {
        "pify": true,
        "eth-query": true,
        "safe-event-emitter": true
      },
      "globals": {
        "console.error": true,
        "setTimeout": true,
        "clearTimeout": true
      }
    },
    "async": {
      "packages": {
        "lodash": true
      },
      "globals": {
        "setImmediate": true,
        "process": true,
        "setTimeout": true
      }
    },
    "xhr": {
      "packages": {
        "global": true,
        "is-function": true,
        "parse-headers": true,
        "xtend": true
      },
      "globals": {
        "setTimeout": true,
        "clearTimeout": true
      }
    },
    "request": {
      "packages": {
        "extend": true,
        "tough-cookie": true,
        "json-stringify-safe": true,
        "safe-buffer": true,
        "aws-sign2": true,
        "aws4": true,
        "http-signature": true,
        "mime-types": true,
        "caseless": true,
        "forever-agent": true,
        "form-data": true,
        "isstream": true,
        "is-typedarray": true,
        "performance-now": true,
        "qs": true,
        "har-validator": true,
        "uuid": true,
        "oauth-sign": true,
        "combined-stream": true,
        "tunnel-agent": true
      },
      "globals": {
        "setImmediate": true,
        "process.nextTick": true,
        "process.version.replace": true,
        "process.env.NODE_DEBUG": true,
        "console.error": true,
        "console.warn": true,
        "setTimeout": true,
        "clearTimeout": true,
        "process.env.NO_PROXY": true,
        "process.env.no_proxy": true,
        "process.env.HTTP_PROXY": true,
        "process.env.http_proxy": true,
        "process.env.HTTPS_PROXY": true,
        "process.env.https_proxy": true
      },
      "builtin": {
        "crypto.createHash": true,
        "crypto.createHmac": true,
        "crypto.randomBytes": true,
        "fs.createReadStream": true,
        "http": true,
        "https": true,
        "querystring": true,
        "stream.Stream": true,
        "url.format": true,
        "url.parse": true,
        "url.resolve": true,
        "util": true,
        "zlib.Z_SYNC_FLUSH": true,
        "zlib.createGunzip": true,
        "zlib.createInflate": true
      }
    },
    "eth-json-rpc-errors": {
      "packages": {
        "fast-safe-stringify": true
      }
    },
    "ethereumjs-tx": {
      "packages": {
        "ethereumjs-util": true,
        "ethereum-common": true
      },
      "globals": {
        "Buffer": true
      }
    },
    "eth-sig-util": {
      "packages": {
        "ethereumjs-util": true,
        "ethereumjs-abi": true
      }
    },
    "finalhandler": {
      "packages": {
        "debug": true,
        "encodeurl": true,
        "escape-html": true,
        "on-finished": true,
        "parseurl": true,
        "statuses": true,
        "unpipe": true
      },
      "globals": {
        "setImmediate": true,
        "process.nextTick": true,
        "process.env.NODE_ENV": true,
        "Buffer.byteLength": true
      }
    },
    "methods": {
      "builtin": {
        "http.METHODS": true
      }
    },
    "parseurl": {
      "builtin": {
        "url.Url": true,
        "url.parse": true
      }
    },
    "accepts": {
      "packages": {
        "negotiator": true,
        "mime-types": true
      }
    },
    "proxy-addr": {
      "packages": {
        "forwarded": true,
        "ipaddr.js": true
      }
    },
    "inherits": {
      "builtin": {
        "util.inherits": true
      }
    },
    "mime-types": {
      "packages": {
        "mime-db": true
      },
      "builtin": {
        "path.extname": true
      }
    },
    "raw-body": {
      "packages": {
        "bytes": true,
        "http-errors": true,
        "iconv-lite": true,
        "unpipe": true
      },
      "globals": {
        "process.nextTick": true,
        "Buffer.concat": true
      }
    },
    "on-finished": {
      "packages": {
        "ee-first": true
      },
      "globals": {
        "setImmediate": true,
        "process.nextTick": true
      }
    },
    "iconv-lite": {
      "packages": {
        "safer-buffer": true
      },
      "globals": {
        "console.error": true,
        "process": true
      },
      "builtin": {
        "buffer.Buffer": true,
        "buffer.SlowBuffer.byteLength": true,
        "buffer.SlowBuffer.prototype.toString": true,
        "buffer.SlowBuffer.prototype.write": true,
        "stream.Readable.prototype.collect": true,
        "stream.Readable.prototype.setEncoding": true,
        "stream.Transform.call": true,
        "stream.Transform.prototype": true,
        "string_decoder.StringDecoder.call": true,
        "string_decoder.StringDecoder.prototype": true
      }
    },
    "secp256k1": {
      "packages": {
        "node-gyp-build": true,
        "elliptic": true
      },
      "globals": {
        "__dirname": true,
        "contextRandomize": true,
        "privateKeyVerify": true,
        "privateKeyNegate": true,
        "privateKeyTweakAdd": true,
        "privateKeyTweakMul": true,
        "publicKeyVerify": true,
        "publicKeyCreate": true,
        "publicKeyConvert": true,
        "publicKeyNegate": true,
        "publicKeyCombine": true,
        "publicKeyTweakAdd": true,
        "publicKeyTweakMul": true,
        "signatureNormalize": true,
        "signatureExport": true,
        "signatureImport": true,
        "ecdsaSign": true,
        "ecdsaVerify": true,
        "ecdsaRecover": true,
        "ecdh": true
      }
    },
    "keccak": {
      "packages": {
        "node-gyp-build": true
      },
      "globals": {
        "__dirname": true,
        "Buffer.alloc": true,
        "Buffer.isBuffer": true,
        "Buffer.from": true
      },
      "builtin": {
        "stream.Transform": true
      }
    },
    "json-stable-stringify": {
      "packages": {
        "jsonify": true
      }
    },
    "is-function": {
      "globals": {
        "setTimeout": true,
        "alert": true,
        "confirm": true,
        "prompt": true
      }
    },
    "ethereumjs-abi": {
      "packages": {
        "ethereumjs-util": true,
        "bn.js": true
      },
      "globals": {
        "Buffer": true
      }
    },
    "safe-buffer": {
      "builtin": {
        "buffer": true
      }
    },
    "content-disposition": {
      "packages": {
        "safe-buffer": true
      },
      "builtin": {
        "path.basename": true
      }
    },
    "cookie-signature": {
      "builtin": {
        "crypto.createHash": true,
        "crypto.createHmac": true
      }
    },
    "send": {
      "packages": {
        "http-errors": true,
        "debug": true,
        "depd": true,
        "destroy": true,
        "encodeurl": true,
        "escape-html": true,
        "etag": true,
        "fresh": true,
        "mime": true,
        "ms": true,
        "on-finished": true,
        "range-parser": true,
        "statuses": true
      },
      "globals": {
        "Buffer.byteLength": true
      },
      "builtin": {
        "fs.createReadStream": true,
        "fs.stat": true,
        "path.extname": true,
        "path.join": true,
        "path.normalize": true,
        "path.resolve": true,
        "path.sep": true,
        "stream": true,
        "util.inherits": true
      }
    },
    "semaphore": {
      "globals": {
        "setTimeout": true,
        "process": true,
        "define": true
      }
    },
    "etag": {
      "globals": {
        "Buffer.byteLength": true,
        "Buffer.isBuffer": true
      },
      "builtin": {
        "crypto.createHash": true,
        "fs.Stats": true
      }
    },
    "safer-buffer": {
      "globals": {
        "process.binding": true
      },
      "builtin": {
        "buffer": true
      }
    },
    "randombytes": {
      "builtin": {
        "crypto.randomBytes": true
      }
    },
    "eth-query": {
      "packages": {
        "xtend": true,
        "json-rpc-random-id": true
      }
    },
    "safe-event-emitter": {
      "packages": {
        "events": true
      },
      "globals": {
        "setTimeout": true
      },
      "builtin": {
        "util.inherits": true
      }
    },
    "destroy": {
      "builtin": {
        "fs.ReadStream": true,
        "stream": true
      }
    },
    "mime": {
      "globals": {
        "process.env.DEBUG_MIME": true,
        "console.warn": true
      },
      "builtin": {
        "fs.readFileSync": true,
        "path": true
      }
    },
    "tough-cookie": {
      "packages": {
        "psl": true
      },
      "globals": {
        "console.warn": true
      },
      "builtin": {
        "net.isIP": true,
        "punycode": true,
        "url.parse": true,
        "util.inherits": true,
        "util.inspect": true
      }
    },
    "aws-sign2": {
      "builtin": {
        "crypto.createHmac": true,
        "url.parse": true
      }
    },
    "aws4": {
      "globals": {
        "Buffer.byteLength": true,
        "process.env": true
      },
      "builtin": {
        "crypto.createHash": true,
        "crypto.createHmac": true,
        "querystring.parse": true,
        "querystring.stringify": true,
        "url.parse": true
      }
    },
    "http-signature": {
      "packages": {
        "assert-plus": true,
        "sshpk": true,
        "jsprim": true
      },
      "globals": {
        "Buffer": true
      },
      "builtin": {
        "crypto.createHmac": true,
        "http": true,
        "util.format": true,
        "util.inherits": true
      }
    },
    "forever-agent": {
      "builtin": {
        "http.Agent": true,
        "https.Agent.prototype.addRequest": true,
        "net.createConnection": true,
        "tls.connect": true,
        "util.inherits": true
      }
    },
    "form-data": {
      "packages": {
        "combined-stream": true,
        "mime-types": true,
        "asynckit": true
      },
      "globals": {
        "Buffer.isBuffer": true,
        "Buffer.byteLength": true,
        "process.nextTick": true
      },
      "builtin": {
        "fs.stat": true,
        "http.request": true,
        "https.request": true,
        "path.basename": true,
        "path.normalize": true,
        "url.parse": true,
        "util.inherits": true,
        "util.isArray": true
      }
    },
    "isstream": {
      "builtin": {
        "stream.Stream": true
      }
    },
    "performance-now": {
      "globals": {
        "performance": true,
        "process": true
      }
    },
    "big-integer": {
      "globals": {
        "BigInt": true,
        "define": true
      }
    },
    "node-gyp-build": {
      "globals": {
        "__webpack_require__": true,
        "__non_webpack_require__": true,
        "process": true
      },
      "builtin": {
        "fs.existsSync": true,
        "fs.readdirSync": true,
        "os.arch": true,
        "os.platform": true,
        "path.dirname": true,
        "path.join": true,
        "path.resolve": true
      }
    },
    "ip-address": {
      "packages": {
        "jsbn": true,
        "lodash.merge": true,
        "sprintf": true,
        "lodash.find": true
      }
    },
    "elliptic": {
      "packages": {
        "brorand": true,
        "bn.js": true,
        "minimalistic-assert": true,
        "minimalistic-crypto-utils": true,
        "hash.js": true,
        "hmac-drbg": true,
        "inherits": true
      }
    },
    "combined-stream": {
      "packages": {
        "delayed-stream": true
      },
      "globals": {
        "Buffer.isBuffer": true
      },
      "builtin": {
        "stream.Stream": true,
        "util.inherits": true
      }
    },
    "asynckit": {
      "globals": {
        "setImmediate": true,
        "process": true,
        "setTimeout": true
      }
    },
    "har-validator": {
      "packages": {
        "ajv": true,
        "har-schema": true
      }
    },
    "uuid": {
      "builtin": {
        "crypto.randomBytes": true
      }
    },
    "oauth-sign": {
      "builtin": {
        "crypto.createHmac": true,
        "crypto.createSign": true
      }
    },
    "tunnel-agent": {
      "packages": {
        "safe-buffer": true
      },
      "globals": {
        "process.nextTick": true,
        "process.env.NODE_DEBUG": true,
        "console": true
      },
      "builtin": {
        "assert.equal": true,
        "events.EventEmitter": true,
        "http.Agent.defaultMaxSockets": true,
        "http.request": true,
        "https.request": true,
        "net": true,
        "tls.connect": true,
        "util.inherits": true
      }
    },
    "brorand": {
      "globals": {
        "crypto": true,
        "msCrypto": true
      },
      "builtin": {
        "crypto.randomBytes": true
      }
    },
    "psl": {
      "builtin": {
        "punycode.toASCII": true
      }
    },
    "assert-plus": {
      "globals": {
        "Buffer.isBuffer": true,
        "process.env.NODE_NDEBUG": true
      },
      "builtin": {
        "assert": true,
        "stream.Stream": true,
        "util.format": true
      }
    },
    "sshpk": {
      "packages": {
        "assert-plus": true,
        "safer-buffer": true,
        "asn1": true,
        "tweetnacl": true,
        "ecc-jsbn": true,
        "jsbn": true,
        "bcrypt-pbkdf": true
      },
      "globals": {
        "Buffer.isBuffer": true
      },
      "builtin": {
        "crypto": true,
        "stream.Writable": true,
        "util": true
      }
    },
    "delayed-stream": {
      "builtin": {
        "stream.Stream": true,
        "util.inherits": true
      }
    },
    "ajv": {
      "packages": {
        "fast-json-stable-stringify": true,
        "uri-js": true,
        "fast-deep-equal": true,
        "json-schema-traverse": true
      },
      "globals": {
        "console": true
      }
    },
    "jsprim": {
      "packages": {
        "assert-plus": true,
        "extsprintf": true,
        "verror": true,
        "json-schema": true
      },
      "builtin": {
        "util": true
      }
    },
    "lodash.merge": {
      "packages": {
        "lodash._arraycopy": true,
        "lodash._arrayeach": true,
        "lodash._createassigner": true,
        "lodash.isarguments": true,
        "lodash.isarray": true,
        "lodash.isplainobject": true,
        "lodash.istypedarray": true,
        "lodash.keys": true,
        "lodash.toplainobject": true
      }
    },
    "lodash.find": {
      "packages": {
        "lodash._basecallback": true,
        "lodash._baseeach": true,
        "lodash._basefind": true,
        "lodash._basefindindex": true,
        "lodash.isarray": true
      }
    },
    "hash.js": {
      "packages": {
        "minimalistic-assert": true,
        "inherits": true
      }
    },
    "hmac-drbg": {
      "packages": {
        "hash.js": true,
        "minimalistic-crypto-utils": true,
        "minimalistic-assert": true
      }
    },
    "jsbn": {
      "globals": {
        "navigator": true,
        "DV": true,
        "crypto": true
      }
    },
    "extsprintf": {
      "globals": {
        "process.stdout": true
      },
      "builtin": {
        "assert.equal": true,
        "util.inspect": true
      }
    },
    "verror": {
      "packages": {
        "assert-plus": true,
        "extsprintf": true,
        "core-util-is": true
      },
      "builtin": {
        "util.inherits": true
      }
    },
    "json-schema": {
      "globals": {
        "define": true
      }
    },
    "lodash._createassigner": {
      "packages": {
        "lodash._bindcallback": true,
        "lodash._isiterateecall": true,
        "lodash.restparam": true
      }
    },
    "lodash.isplainobject": {
      "packages": {
        "lodash._basefor": true,
        "lodash.isarguments": true,
        "lodash.keysin": true
      }
    },
    "lodash.keys": {
      "packages": {
        "lodash._getnative": true,
        "lodash.isarguments": true,
        "lodash.isarray": true
      }
    },
    "lodash.toplainobject": {
      "packages": {
        "lodash._basecopy": true,
        "lodash.keysin": true
      }
    },
    "lodash._basecallback": {
      "packages": {
        "lodash._baseisequal": true,
        "lodash._bindcallback": true,
        "lodash.isarray": true,
        "lodash.pairs": true
      }
    },
    "lodash._baseeach": {
      "packages": {
        "lodash.keys": true
      }
    },
    "asn1": {
      "packages": {
        "safer-buffer": true
      },
      "builtin": {
        "assert.equal": true,
        "assert.ok": true
      }
    },
    "core-util-is": {
      "globals": {
        "Buffer.isBuffer": true
      }
    },
    "lodash.keysin": {
      "packages": {
        "lodash.isarguments": true,
        "lodash.isarray": true
      }
    },
    "lodash._baseisequal": {
      "packages": {
        "lodash.isarray": true,
        "lodash.istypedarray": true,
        "lodash.keys": true
      }
    },
    "lodash.pairs": {
      "packages": {
        "lodash.keys": true
      }
    },
    "tweetnacl": {
      "globals": {
        "crypto": true,
        "msCrypto": true,
        "nacl": "write"
      },
      "builtin": {
        "crypto": true
      }
    },
    "uri-js": {
      "globals": {
        "define": true
      }
    },
    "ecc-jsbn": {
      "packages": {
        "jsbn": true,
        "safer-buffer": true
      },
      "globals": {
        "q": true,
        "modDouble": true,
        "SecureRandom": true
      },
      "builtin": {
        "crypto.randomBytes": true
      }
    },
    "bcrypt-pbkdf": {
      "packages": {
        "tweetnacl": true
      }
    }
  }
}